{
  "type": "FeatureCollection",
  "features": [
    {
      "type": "Feature",
      "properties": {
        "name": "铜陵县"
      },
      "geometry": {
        "type": "MultiPolygon",
        "coordinates": [
          [
            [
              [
                117.890030546875,
                31.0795876289063
              ],
              [
                117.936812773438,
                31.0748195625
              ],
              [
                117.977345,
                31.083843
              ],
              [
                117.99213015625,
                31.0772194648438
              ],
              [
                118.009600859375,
                31.0826589179688
              ],
              [
                118.013902617188,
                31.068843
              ],
              [
                118.003961210938,
                31.0369240546876
              ],
              [
                118.075909453125,
                31.0124050117188
              ],
              [
                118.096939726563,
                30.9782692695313
              ],
              [
                118.153531523438,
                30.9700295234375
              ],
              [
                118.157345,
                30.963843
              ],
              [
                118.150416289063,
                30.9578713203125
              ],
              [
                118.152745390625,
                30.928843
              ],
              [
                118.151944609375,
                30.918843
              ],
              [
                118.1527746875,
                30.9084889960938
              ],
              [
                118.12197390625,
                30.89921409375
              ],
              [
                118.072633085938,
                30.8684181953125
              ],
              [
                118.051373320313,
                30.8701271796875
              ],
              [
                118.024757109375,
                30.8392311835937
              ],
              [
                118.017345,
                30.8638430000001
              ],
              [
                118.009658,
                30.865059
              ],
              [
                118.007345,
                30.8638430000001
              ],
              [
                117.980704375,
                30.850483625
              ],
              [
                117.977345,
                30.843843
              ],
              [
                117.97142703125,
                30.8397585273437
              ],
              [
                117.95959109375,
                30.8226125312501
              ],
              [
                117.932266875,
                30.8404055
              ],
              [
                117.90326296875,
                30.8179274726563
              ],
              [
                117.87142703125,
                30.8097585273438
              ],
              [
                117.84201296875,
                30.7906032539062
              ],
              [
                117.827432890625,
                30.7694899726563
              ],
              [
                117.80142703125,
                30.7597585273437
              ],
              [
                117.797345,
                30.753843
              ],
              [
                117.776817,
                30.761345
              ],
              [
                117.776242,
                30.771771
              ],
              [
                117.764744,
                30.773757
              ],
              [
                117.756519804688,
                30.7643190742188
              ],
              [
                117.743472,
                30.773757
              ],
              [
                117.755545,
                30.785174
              ],
              [
                117.758599,
                30.793085
              ],
              [
                117.767798,
                30.799537
              ],
              [
                117.781884,
                30.811696
              ],
              [
                117.79137,
                30.82559
              ],
              [
                117.794172,
                30.842583
              ],
              [
                117.81027,
                30.860689
              ],
              [
                117.812138,
                30.862425
              ],
              [
                117.813863,
                30.863665
              ],
              [
                117.814294,
                30.863913
              ],
              [
                117.816235,
                30.865152
              ],
              [
                117.817528,
                30.867136
              ],
              [
                117.817313,
                30.868562
              ],
              [
                117.818247,
                30.868624
              ],
              [
                117.818319,
                30.869926
              ],
              [
                117.819325,
                30.870112
              ],
              [
                117.818822,
                30.871166
              ],
              [
                117.819325,
                30.87284
              ],
              [
                117.820475,
                30.874513
              ],
              [
                117.822487,
                30.876249
              ],
              [
                117.824355,
                30.877241
              ],
              [
                117.827086,
                30.877613
              ],
              [
                117.829673,
                30.879473
              ],
              [
                117.830967,
                30.881084
              ],
              [
                117.833842,
                30.883192
              ],
              [
                117.838585,
                30.885423
              ],
              [
                117.840884,
                30.889638
              ],
              [
                117.847783,
                30.891683
              ],
              [
                117.858994,
                30.895898
              ],
              [
                117.868193,
                30.902095
              ],
              [
                117.876816,
                30.911515
              ],
              [
                117.881991,
                30.924403
              ],
              [
                117.892339,
                30.933324
              ],
              [
                117.88774,
                30.941749
              ],
              [
                117.896938,
                30.982873
              ],
              [
                117.864168,
                30.987331
              ],
              [
                117.844046,
                30.982377
              ],
              [
                117.837722,
                30.980396
              ],
              [
                117.827374,
                30.979901
              ],
              [
                117.820066,
                30.965421
              ],
              [
                117.819967,
                30.965309
              ],
              [
                117.819828,
                30.965274
              ],
              [
                117.819253,
                30.964713
              ],
              [
                117.819145,
                30.964589
              ],
              [
                117.817345,
                30.9438430000001
              ],
              [
                117.791695585938,
                30.9501442695313
              ],
              [
                117.787345,
                30.9438430000001
              ],
              [
                117.767345,
                30.9438430000001
              ],
              [
                117.767345,
                30.9338430000001
              ],
              [
                117.737345,
                30.913843
              ],
              [
                117.733985625,
                30.960483625
              ],
              [
                117.727345,
                30.9738430000001
              ],
              [
                117.732784453125,
                31.0283229804688
              ],
              [
                117.768214140625,
                31.1100221992188
              ],
              [
                117.835186796875,
                31.1483815742188
              ],
              [
                117.867388945313,
                31.1317946601563
              ],
              [
                117.890030546875,
                31.0795876289063
              ]
            ]
          ]
        ]
      }
    },
    {
      "type": "Feature",
      "properties": {
        "name": "铜陵市"
      },
      "geometry": {
        "type": "MultiPolygon",
        "coordinates": [
          [
            [
              [
                117.767349,
                30.933878
              ],
              [
                117.767353,
                30.943844
              ],
              [
                117.787413,
                30.943879
              ],
              [
                117.791702,
                30.950131
              ],
              [
                117.817434,
                30.943654
              ],
              [
                117.819015,
                30.963087
              ],
              [
                117.819145,
                30.964593
              ],
              [
                117.819832,
                30.965282
              ],
              [
                117.819967,
                30.965313
              ],
              [
                117.820093,
                30.965456
              ],
              [
                117.82749,
                30.979901
              ],
              [
                117.837947,
                30.980396
              ],
              [
                117.844271,
                30.982408
              ],
              [
                117.864069,
                30.987331
              ],
              [
                117.896983,
                30.982904
              ],
              [
                117.887857,
                30.941687
              ],
              [
                117.892348,
                30.933138
              ],
              [
                117.882,
                30.924279
              ],
              [
                117.876897,
                30.911515
              ],
              [
                117.868417,
                30.902157
              ],
              [
                117.858464,
                30.895588
              ],
              [
                117.847613,
                30.89159
              ],
              [
                117.840857,
                30.889576
              ],
              [
                117.838629,
                30.885454
              ],
              [
                117.833868,
                30.883269
              ],
              [
                117.83103,
                30.881162
              ],
              [
                117.829646,
                30.879457
              ],
              [
                117.827041,
                30.877559
              ],
              [
                117.825748,
                30.877435
              ],
              [
                117.824293,
                30.877202
              ],
              [
                117.822568,
                30.876257
              ],
              [
                117.820969,
                30.875017
              ],
              [
                117.820106,
                30.874025
              ],
              [
                117.819208,
                30.872631
              ],
              [
                117.818849,
                30.871267
              ],
              [
                117.81928,
                30.87012
              ],
              [
                117.818382,
                30.869872
              ],
              [
                117.818094,
                30.868632
              ],
              [
                117.817268,
                30.868446
              ],
              [
                117.817447,
                30.86702
              ],
              [
                117.816154,
                30.86516
              ],
              [
                117.81159,
                30.862184
              ],
              [
                117.794199,
                30.842281
              ],
              [
                117.791253,
                30.82535
              ],
              [
                117.781695,
                30.811518
              ],
              [
                117.768472,
                30.800042
              ],
              [
                117.758555,
                30.793031
              ],
              [
                117.755428,
                30.785042
              ],
              [
                117.74349,
                30.773726
              ],
              [
                117.731848,
                30.774218
              ],
              [
                117.726099,
                30.780175
              ],
              [
                117.734722,
                30.786132
              ],
              [
                117.724949,
                30.78911
              ],
              [
                117.706552,
                30.775211
              ],
              [
                117.690454,
                30.767268
              ],
              [
                117.68528,
                30.771239
              ],
              [
                117.703102,
                30.795563
              ],
              [
                117.709426,
                30.799534
              ],
              [
                117.725524,
                30.826827
              ],
              [
                117.726099,
                30.849152
              ],
              [
                117.73731,
                30.913896
              ],
              [
                117.767349,
                30.933878
              ]
            ]
          ]
        ]
      }
    }
  ]
}