{
  "type": "FeatureCollection",
  "features": [
    {
      "type": "Feature",
      "properties": {
        "name": "凤台县"
      },
      "geometry": {
        "type": "MultiPolygon",
        "coordinates": [
          [
            [
              [
                116.68326296875,
                32.8779274726563
              ],
              [
                116.66326296875,
                32.8472145820313
              ],
              [
                116.67310671875,
                32.799858625
              ],
              [
                116.694459257813,
                32.7859548164063
              ],
              [
                116.719112578125,
                32.7914821601563
              ],
              [
                116.73326296875,
                32.7697585273438
              ],
              [
                116.74142703125,
                32.7479274726563
              ],
              [
                116.75326296875,
                32.7397585273438
              ],
              [
                116.767667265625,
                32.718891828125
              ],
              [
                116.787345,
                32.713843
              ],
              [
                116.780704375,
                32.7004836250001
              ],
              [
                116.773985625,
                32.667202375
              ],
              [
                116.767345,
                32.6538430000001
              ],
              [
                116.752232695313,
                32.6613552070312
              ],
              [
                116.733985625,
                32.6509596992188
              ],
              [
                116.747222929688,
                32.6238527656251
              ],
              [
                116.687457304688,
                32.5938283515625
              ],
              [
                116.673985625,
                32.5672023750001
              ],
              [
                116.640704375,
                32.560483625
              ],
              [
                116.627345,
                32.553843
              ],
              [
                116.62298953125,
                32.57948753125
              ],
              [
                116.602266875,
                32.5954811835938
              ],
              [
                116.548350859375,
                32.587514875
              ],
              [
                116.52162234375,
                32.6528224921875
              ],
              [
                116.50170046875,
                32.6681984687501
              ],
              [
                116.49298953125,
                32.6794875312501
              ],
              [
                116.438951445313,
                32.6908888984376
              ],
              [
                116.443824492188,
                32.7238430000001
              ],
              [
                116.438648710938,
                32.758843
              ],
              [
                116.443082304688,
                32.788843
              ],
              [
                116.434268828125,
                32.8484987617188
              ],
              [
                116.41869265625,
                32.8605202460938
              ],
              [
                116.397345,
                32.8573659492188
              ],
              [
                116.380128203125,
                32.8599098945313
              ],
              [
                116.387345,
                32.903843
              ],
              [
                116.383531523438,
                32.9200295234375
              ],
              [
                116.360601835938,
                32.9483425117188
              ],
              [
                116.373912382813,
                32.9888112617187
              ],
              [
                116.370538359375,
                32.9996486640625
              ],
              [
                116.377345,
                33.003843
              ],
              [
                116.60142703125,
                32.9479274726563
              ],
              [
                116.69326296875,
                32.9397585273438
              ],
              [
                116.707345,
                32.933843
              ],
              [
                116.69142703125,
                32.9097585273438
              ],
              [
                116.68326296875,
                32.8779274726563
              ]
            ]
          ]
        ]
      }
    },
    {
      "type": "Feature",
      "properties": {
        "name": "淮南市"
      },
      "geometry": {
        "type": "MultiPolygon",
        "coordinates": [
          [
            [
              [
                116.95197390625,
                32.79847190625
              ],
              [
                117.004205351563,
                32.7751638007813
              ],
              [
                117.02271609375,
                32.75921409375
              ],
              [
                117.048853789063,
                32.7288796210938
              ],
              [
                117.087345,
                32.7238430000001
              ],
              [
                117.078075,
                32.746382
              ],
              [
                117.124643,
                32.759986
              ],
              [
                117.19622,
                32.733749
              ],
              [
                117.174086,
                32.69924
              ],
              [
                117.158563,
                32.687815
              ],
              [
                117.187021,
                32.614855
              ],
              [
                117.182422,
                32.609745
              ],
              [
                117.132117,
                32.598796
              ],
              [
                117.122631,
                32.599039
              ],
              [
                117.109408,
                32.597336
              ],
              [
                117.037399,
                32.614125
              ],
              [
                116.962229,
                32.608894
              ],
              [
                116.942682,
                32.609624
              ],
              [
                116.93722,
                32.604149
              ],
              [
                116.93219,
                32.577318
              ],
              [
                116.906031,
                32.558087
              ],
              [
                116.866075,
                32.543965
              ],
              [
                116.852851,
                32.547131
              ],
              [
                116.820369,
                32.567825
              ],
              [
                116.795216,
                32.62112
              ],
              [
                116.791335,
                32.625499
              ],
              [
                116.788461,
                32.643742
              ],
              [
                116.767189,
                32.653896
              ],
              [
                116.774088,
                32.667027
              ],
              [
                116.780987,
                32.700273
              ],
              [
                116.787311,
                32.713883
              ],
              [
                116.767692,
                32.719048
              ],
              [
                116.75326296875,
                32.7397585273438
              ],
              [
                116.74142703125,
                32.7479274726563
              ],
              [
                116.73326296875,
                32.7697585273438
              ],
              [
                116.719112578125,
                32.7914821601563
              ],
              [
                116.694459257813,
                32.7859548164063
              ],
              [
                116.67310671875,
                32.799858625
              ],
              [
                116.66326296875,
                32.8472145820313
              ],
              [
                116.68326296875,
                32.8779274726563
              ],
              [
                116.69142703125,
                32.9097585273438
              ],
              [
                116.707345,
                32.933843
              ],
              [
                116.737345,
                32.933843
              ],
              [
                116.79271609375,
                32.90921409375
              ],
              [
                116.806402617188,
                32.8933278632813
              ],
              [
                116.95197390625,
                32.79847190625
              ]
            ]
          ]
        ]
      }
    }
  ]
}